{
  "products_list": [
    {
      "color": "Yellow Gold",
      "laborPerGram": 23,
      "taxable": true,
      "name": "21k Kursi Jaber Full Set",
      "featured": true,
      "karat": 21,
      "outOfStock": false,
      "isDynamic": true,
      "marginPercent": 9,
      "weight": "91.50",
      "id": "KJ1",
      "image": "assets/koursi-jaber-91.50.png",
      "description": "full set",
      "category": "kladas"
    },
    {
      "color": "Yellow Gold",
      "laborPerGram": 6,
      "taxable": true,
      "name": "Klada ( Coin necklace ) ",
      "featured": true,
      "karat": 21,
      "outOfStock": false,
      "isDynamic": true,
      "marginPercent": 10,
      "weight": "144.30",
      "id": "Kc1",
      "image": "assets/klada1-144.30.png",
      "description": "cooin necklace set",
      "category": "kladas"
    }
  ]
}
